pyiron_potentialfit/__init__.py
pyiron_potentialfit/_version.py
pyiron_potentialfit/assyst/__init__.py
pyiron_potentialfit/assyst/projectflow.py
pyiron_potentialfit/assyst/util.py
pyiron_potentialfit/assyst/vasp.py
pyiron_potentialfit/assyst/calculations/__init__.py
pyiron_potentialfit/assyst/calculations/workflow.py
pyiron_potentialfit/assyst/jobfactories/__init__.py
pyiron_potentialfit/assyst/repair/__init__.py
pyiron_potentialfit/assyst/structures/__init__.py
pyiron_potentialfit/assyst/structures/job.py
pyiron_potentialfit/assyst/structures/minimize.py
pyiron_potentialfit/assyst/structures/random.py
pyiron_potentialfit/assyst/structures/spg.py
pyiron_potentialfit/assyst/structures/workflow.py
pyiron_potentialfit/atomicrex/__init__.py
pyiron_potentialfit/atomicrex/atomicrex_job.py
pyiron_potentialfit/atomicrex/base.py
pyiron_potentialfit/atomicrex/fit_properties.py
pyiron_potentialfit/atomicrex/function_factory.py
pyiron_potentialfit/atomicrex/general_input.py
pyiron_potentialfit/atomicrex/interactive.py
pyiron_potentialfit/atomicrex/output.py
pyiron_potentialfit/atomicrex/parameter_constraints.py
pyiron_potentialfit/atomicrex/potential_factory.py
pyiron_potentialfit/atomicrex/structure_list.py
pyiron_potentialfit/atomicrex/utility_functions.py
pyiron_potentialfit/atomistics/__init__.py
pyiron_potentialfit/atomistics/job/__init__.py
pyiron_potentialfit/atomistics/job/structurelistmasterinteractive.py
pyiron_potentialfit/atomistics/job/trainingcontainer.py
pyiron_potentialfit/meamfit/__init__.py
pyiron_potentialfit/meamfit/meamfit.py
pyiron_potentialfit/ml/__init__.py
pyiron_potentialfit/ml/potentialfit.py
pyiron_potentialfit/mlip/__init__.py
pyiron_potentialfit/mlip/cfgs.py
pyiron_potentialfit/mlip/lammps.py
pyiron_potentialfit/mlip/masters.py
pyiron_potentialfit/mlip/mlip.py
pyiron_potentialfit/mlip/mlipdescriptors.py
pyiron_potentialfit/mlip/parser.py
pyiron_potentialfit/mlip/potential.py
pyiron_potentialfit/pacemaker/__init__.py
pyiron_potentialfit-0.3.13.dist-info/licenses/LICENSE
pyiron_potentialfit-0.3.13.dist-info/METADATA
pyiron_potentialfit-0.3.13.dist-info/WHEEL
pyiron_potentialfit-0.3.13.dist-info/entry_points.txt
pyiron_potentialfit-0.3.13.dist-info/top_level.txt
pyiron_potentialfit-0.3.13.dist-info/RECORD
