Metadata-Version: 2.4
Name: pyiron_potentialfit
Version: 0.3.13
Summary: Repository for user-generated plugins to the pyiron IDE.
Home-page: https://github.com/pyiron/pyiron_potentialfit
Author: Max-Planck-Institut für Eisenforschung GmbH - Computational Materials Design (CM) Department
Author-email: huber@mpie.de
License: BSD
Keywords: pyiron
Classifier: Development Status :: 4 - Beta
Classifier: Topic :: Scientific/Engineering :: Physics
Classifier: License :: OSI Approved :: BSD License
Classifier: Intended Audience :: Science/Research
Classifier: Operating System :: OS Independent
Classifier: Programming Language :: Python :: 3.11
Classifier: Programming Language :: Python :: 3.12
License-File: LICENSE
Requires-Dist: ase>=3.25.0
Requires-Dist: matplotlib<4,>=3.8.4
Requires-Dist: numpy>=1.26.4
Requires-Dist: pyiron_base>=0.15.0
Requires-Dist: pyiron_atomistics>=0.7.19
Requires-Dist: scipy>=1.15.2
Requires-Dist: runnerase>=0.3.3
Requires-Dist: pyiron_snippets<2,>=0.1.1
Requires-Dist: pyparsing<3.2,>=3.1.2
Requires-Dist: dill>=0.3.0
Requires-Dist: seaborn<0.14,>=0.13.0
Requires-Dist: pyxtal<1.1,>=0.6.0
Dynamic: author
Dynamic: author-email
Dynamic: classifier
Dynamic: description
Dynamic: home-page
Dynamic: keywords
Dynamic: license
Dynamic: license-file
Dynamic: requires-dist
Dynamic: summary
